{
    "results": [
        {
            "ButtonCircle": []
        },
        {
            "ButtonSquare": [
                {
                    "score": "0.99922717",
                    "bl_point": [
                        "174.20709",
                        "22.265495"
                    ],
                    "width": "148.75626",
                    "height": "96.05063"
                },
                {
                    "score": "0.9978798",
                    "bl_point": [
                        "169.61588",
                        "169.30574"
                    ],
                    "width": "174.32336",
                    "height": "93.426254"
                },
                {
                    "score": "0.8990806",
                    "bl_point": [
                        "260.68585",
                        "347.60464"
                    ],
                    "width": "101.236084",
                    "height": "88.10974"
                }
            ]
        },
        {
            "CheckBox": [
                {
                    "score": "0.9987484",
                    "bl_point": [
                        "9.570801",
                        "340.75574"
                    ],
                    "width": "426.21634",
                    "height": "121.61383"
                },
                {
                    "score": "0.9789288",
                    "bl_point": [
                        "261.23645",
                        "351.9875"
                    ],
                    "width": "237.18463",
                    "height": "85.20245"
                },
                {
                    "score": "0.80014884",
                    "bl_point": [
                        "7.355118",
                        "22.592136"
                    ],
                    "width": "399.14667",
                    "height": "105.72478"
                }
            ]
        },
        {
            "ImageView": []
        },
        {
            "RadioButton": []
        },
        {
            "TextInput": []
        },
        {
            "Text": [
                {
                    "score": "0.8973681",
                    "bl_point": [
                        "341.13168",
                        "368.9248"
                    ],
                    "width": "134.8728",
                    "height": "54.48047"
                }
            ]
        }
    ]
}